{
  "project_info": {
    "project_number": "282607814954",
    "project_id": "touchhealth-app",
    "storage_bucket": "touchhealth-app.firebasestorage.app"
  },
  "client": [
    {
      "client_info": {
        "mobilesdk_app_id": "1:282607814954:android:bbd26aa0dd4d958e25b653",
        "android_client_info": {
          "package_name": "com.example.touch_health"
        }
      },
      "oauth_client": [
        {
          "client_id": "282607814954-svmklbg57d2aapqf4b7qf15mno40nnn4.apps.googleusercontent.com",
          "client_type": 1,
          "android_info": {
            "package_name": "com.example.touch_health",
            "certificate_hash": "79d3487174ba7c24bf01d596a055b01a495f2d65"
          }
        },
        {
          "client_id": "282607814954-fpo80r68j1pv0cqjkmjr9f99ja45jcha.apps.googleusercontent.com",
          "client_type": 3
        }
      ],
      "api_key": [
        {
          "current_key": "AIzaSyC9L4Lt11E1yCpShLp9Sl8yAqRQ6298Y1U"
        }
      ],
      "services": {
        "appinvite_service": {
          "other_platform_oauth_client": [
            {
              "client_id": "282607814954-fpo80r68j1pv0cqjkmjr9f99ja45jcha.apps.googleusercontent.com",
              "client_type": 3
            }
          ]
        }
      }
    }
  ],
  "configuration_version": "1"
}